MANIFEST.in
requirements.txt
setup.py
slth/__init__.py
slth/__main__.py
slth/components.py
slth/conf.py
slth/endpoints.py
slth/exceptions.py
slth/forms.py
slth/models.py
slth/notifications.py
slth/permissions.py
slth/queryset.py
slth/roles.py
slth/serializer.py
slth/statistics.py
slth/tests.py
slth/urls.py
slth/utils.py
slth/views.py
slth/db/__init__.py
slth/db/models.py
slth/management/__init__.py
slth/management/commands/__init__.py
slth/management/commands/integration_test.py
slth/management/commands/sync.py
slth/migrations/0001_initial.py
slth/migrations/0002_email_role_pushsubscription_error.py
slth/migrations/__init__.py
slth/selenium/__init__.py
slth/selenium/browser.py
slth/static/images/logo.svg
slth_package.egg-info/PKG-INFO
slth_package.egg-info/SOURCES.txt
slth_package.egg-info/dependency_links.txt
slth_package.egg-info/requires.txt
slth_package.egg-info/top_level.txt